[
  {
    "title": "徐伊人的直播间（回放生成中）",
    "subTitle": {
      "raw": "聊会",
      "base64": "6IGK5Lya"
    },
    "picPath": [
      "https://source.48.cn/mediasource/live/15381406364349g28yB5r6j.jpg"
    ],
    "startTime": {
      "timestamp": 1538490840546,
      "datetime": "2018-10-02T22:34:00Z"
    },
    "memberId": 43,
    "liveType": 1,
    "streamPath": "https://live.us.sinaimg.cn/003vovUsjx07o5PEW9LV070d010007fp0k01.m3u8"
  },
  {
    "title": "徐伊人的直播间（回放生成中）",
    "subTitle": {
      "raw": "聊会",
      "base64": "6IGK5Lya"
    },
    "picPath": [
      "https://source.48.cn/mediasource/live/15381406364349g28yB5r6j.jpg"
    ],
    "startTime": {
      "timestamp": 1538140636183,
      "datetime": "2018-09-28T21:17:16Z"
    },
    "memberId": 43,
    "liveType": 1,
    "streamPath": "https://live.us.sinaimg.cn/004obOeKjx07nZmcVgYg070d010006aT0k01.m3u8"
  },
  {
    "title": "徐伊人的直播间（回放生成中）",
    "subTitle": {
      "raw": "Smile～",
      "base64": "U21pbGXvvZ4="
    },
    "picPath": [
      "https://source.48.cn/mediasource/live/15369392673858ieYwiOvgi.jpg"
    ],
    "startTime": {
      "timestamp": 1536939267644,
      "datetime": "2018-09-14T23:34:27Z"
    },
    "memberId": 43,
    "liveType": 1,
    "streamPath": "https://live.us.sinaimg.cn/0035QttZjx07nD8yBSoL070d010002l80k01.m3u8"
  },
  {
    "title": "徐伊人的直播间（回放生成中）",
    "subTitle": {
      "raw": "Smile～",
      "base64": "U21pbGXvvZ4="
    },
    "picPath": [
      "https://source.48.cn/mediasource/live/15364081366431o2IBKXQKJ.jpg"
    ],
    "startTime": {
      "timestamp": 1536408136999,
      "datetime": "2018-09-08T20:02:16Z"
    },
    "memberId": 43,
    "liveType": 1,
    "streamPath": "https://live.us.sinaimg.cn/004oiH8Djx07ntm3jPsj070d010004oT0k01.m3u8"
  },
  {
    "title": "徐伊人的直播间（回放生成中）",
    "subTitle": {
      "raw": "Smile～",
      "base64": "U21pbGXvvZ4="
    },
    "picPath": [
      "https://source.48.cn/mediasource/live/1534502287642Oed70YjA2G.jpg"
    ],
    "startTime": {
      "timestamp": 1536150724017,
      "datetime": "2018-09-05T20:32:04Z"
    },
    "memberId": 43,
    "liveType": 1,
    "streamPath": "https://live.us.sinaimg.cn/001x1O5bjx07noDQ1B1K070d010007Zx0k01.m3u8"
  },
  {
    "title": "徐伊人的直播间（回放生成中）",
    "subTitle": {
      "raw": "Smile~来看我吃火锅啦",
      "base64": "U21pbGV+5p2l55yL5oiR5ZCD54Gr6ZSF5ZWm"
    },
    "picPath": [
      "https://source.48.cn/mediasource/live/1534502287642Oed70YjA2G.jpg"
    ],
    "startTime": {
      "timestamp": 1535644775174,
      "datetime": "2018-08-30T23:59:35Z"
    },
    "memberId": 43,
    "liveType": 1,
    "streamPath": "https://live.us.sinaimg.cn/004btCMNjx07nfgltvB6070d010004wS0k01.m3u8"
  },
  {
    "title": "徐伊人的直播间（回放生成中）",
    "subTitle": {
      "raw": "Smile~来看我吃炸鸡啦",
      "base64": "U21pbGV+5p2l55yL5oiR5ZCD54K46bih5ZWm"
    },
    "picPath": [
      "https://source.48.cn/mediasource/live/1534502287642Oed70YjA2G.jpg"
    ],
    "startTime": {
      "timestamp": 1535543792289,
      "datetime": "2018-08-29T19:56:32Z"
    },
    "memberId": 43,
    "liveType": 1,
    "streamPath": "https://live.us.sinaimg.cn/003voTWmjx07ndnbM9Fe070d0100025b0k01.m3u8"
  },
  {
    "title": "徐伊人的直播间（回放生成中）",
    "subTitle": {
      "raw": "Smile~",
      "base64": "U21pbGV+"
    },
    "picPath": [
      "https://source.48.cn/mediasource/live/1534502287642Oed70YjA2G.jpg"
    ],
    "startTime": {
      "timestamp": 1535455403555,
      "datetime": "2018-08-28T19:23:23Z"
    },
    "memberId": 43,
    "liveType": 1,
    "streamPath": "https://live.us.sinaimg.cn/0009cQy4jx07nbOQ9Kvm070d010009eK0k01.m3u8"
  },
  {
    "title": "徐伊人的直播间（回放生成中）",
    "subTitle": {
      "raw": "随缘吃播",
      "base64": "6ZqP57yY5ZCD5pKt"
    },
    "picPath": [
      "https://source.48.cn/mediasource/live/1534502287642Oed70YjA2G.jpg"
    ],
    "startTime": {
      "timestamp": 1535278024373,
      "datetime": "2018-08-26T18:07:04Z"
    },
    "memberId": 43,
    "liveType": 1,
    "streamPath": "https://live.us.sinaimg.cn/003gEuMYjx07n8tdJfUY070d010002da0k01.m3u8"
  },
  {
    "title": "徐伊人的直播间（回放生成中）",
    "subTitle": {
      "raw": "随缘直播",
      "base64": "6ZqP57yY55u05pKt"
    },
    "picPath": [
      "https://source.48.cn/mediasource/live/1534502287642Oed70YjA2G.jpg"
    ],
    "startTime": {
      "timestamp": 1535202788538,
      "datetime": "2018-08-25T21:13:08Z"
    },
    "memberId": 43,
    "liveType": 1,
    "streamPath": "https://live.us.sinaimg.cn/003oFQ3Gjx07n75P6iGz070d010003te0k01.m3u8"
  },
  {
    "title": "徐伊人的电台（回放生成中）",
    "subTitle": {
      "raw": "捕鱼空隙的聊天",
      "base64": "5o2V6bG856m66ZqZ55qE6IGK5aSp"
    },
    "picPath": [
      "https://source.48.cn/mediasource/live/1535121081585kotNL2zuE7.jpg",
      "https://source.48.cn/mediasource/live/1535121081766Db4t86rIHR.jpg"
    ],
    "startTime": {
      "timestamp": 1535121536051,
      "datetime": "2018-08-24T22:38:56Z"
    },
    "memberId": 43,
    "liveType": 2,
    "streamPath": "https://mp4.48.cn/live/b88ac984-d242-43ca-87aa-a91e39514687.mp4"
  },
  {
    "title": "徐伊人的电台（回放生成中）",
    "subTitle": {
      "raw": "捕鱼空隙的聊天",
      "base64": "5o2V6bG856m66ZqZ55qE6IGK5aSp"
    },
    "picPath": [
      "https://source.48.cn/mediasource/live/1535121081585kotNL2zuE7.jpg",
      "https://source.48.cn/mediasource/live/1535121081766Db4t86rIHR.jpg"
    ],
    "startTime": {
      "timestamp": 1535121082056,
      "datetime": "2018-08-24T22:31:22Z"
    },
    "memberId": 43,
    "liveType": 2,
    "streamPath": "https://mp4.48.cn/live/14673190-7334-4201-9269-1c26ec571f74.mp4"
  },
  {
    "title": "徐伊人的直播间（回放生成中）",
    "subTitle": {
      "raw": "随缘直播",
      "base64": "6ZqP57yY55u05pKt"
    },
    "picPath": [
      "https://source.48.cn/mediasource/live/1534502287642Oed70YjA2G.jpg"
    ],
    "startTime": {
      "timestamp": 1534504745806,
      "datetime": "2018-08-17T19:19:05Z"
    },
    "memberId": 43,
    "liveType": 1,
    "streamPath": "https://live.us.sinaimg.cn/0022LuU6jx07mUceg9if070d010002xy0k01.m3u8"
  },
  {
    "title": "徐伊人的直播间（回放生成中）",
    "subTitle": {
      "raw": "随缘直播",
      "base64": "6ZqP57yY55u05pKt"
    },
    "picPath": [
      "https://source.48.cn/mediasource/live/1534502287642Oed70YjA2G.jpg"
    ],
    "startTime": {
      "timestamp": 1534504272939,
      "datetime": "2018-08-17T19:11:12Z"
    },
    "memberId": 43,
    "liveType": 1,
    "streamPath": "https://live.us.sinaimg.cn/001jjChXjx07mUawiN5R070d010000I20k01.m3u8"
  },
  {
    "title": "徐伊人的直播间（回放生成中）",
    "subTitle": {
      "raw": "随缘直播",
      "base64": "6ZqP57yY55u05pKt"
    },
    "picPath": [
      "https://source.48.cn/mediasource/live/1534502287642Oed70YjA2G.jpg"
    ],
    "startTime": {
      "timestamp": 1534502287856,
      "datetime": "2018-08-17T18:38:07Z"
    },
    "memberId": 43,
    "liveType": 1,
    "streamPath": "https://live.us.sinaimg.cn/004EW7PUjx07mUa3vpAc070d010003uZ0k01.m3u8"
  },
  {
    "title": "徐伊人的直播间（回放生成中）",
    "subTitle": {
      "raw": "半小时～",
      "base64": "5Y2K5bCP5pe2772e"
    },
    "picPath": [
      "https://source.48.cn/mediasource/live/153279247083084A0AES98E.jpg"
    ],
    "startTime": {
      "timestamp": 1533209289988,
      "datetime": "2018-08-02T19:28:09Z"
    },
    "memberId": 43,
    "liveType": 1,
    "streamPath": "https://live.us.sinaimg.cn/004a3AxFjx07mwi49wuA070d010003sk0k01.m3u8"
  },
  {
    "title": "徐伊人的直播间（回放生成中）",
    "subTitle": {
      "raw": "聊聊天说说话～",
      "base64": "6IGK6IGK5aSp6K+06K+06K+d772e"
    },
    "picPath": [
      "https://source.48.cn/mediasource/live/153279247083084A0AES98E.jpg"
    ],
    "startTime": {
      "timestamp": 1532792471152,
      "datetime": "2018-07-28T23:41:11Z"
    },
    "memberId": 43,
    "liveType": 1,
    "streamPath": "https://live.us.sinaimg.cn/000U8GV8jx07moAx5nzh070d010002KS0k01.m3u8"
  },
  {
    "title": "徐伊人的直播间（回放生成中）",
    "subTitle": {
      "raw": "聊聊天说说话～",
      "base64": "6IGK6IGK5aSp6K+06K+06K+d772e"
    },
    "picPath": [
      "https://source.48.cn/mediasource/live/1528387341346f9JZy3Jm4L.jpg"
    ],
    "startTime": {
      "timestamp": 1531656044602,
      "datetime": "2018-07-15T20:00:44Z"
    },
    "memberId": 43,
    "liveType": 1,
    "streamPath": "https://live.us.sinaimg.cn/000th4oFjx07m3Giqtqn070d010009nB0k01.m3u8"
  },
  {
    "title": "徐伊人的直播间（回放生成中）",
    "subTitle": {
      "raw": "～",
      "base64": "772e"
    },
    "picPath": [
      "https://source.48.cn/mediasource/live/1528387341346f9JZy3Jm4L.jpg"
    ],
    "startTime": {
      "timestamp": 1531409310236,
      "datetime": "2018-07-12T23:28:30Z"
    },
    "memberId": 43,
    "liveType": 1,
    "streamPath": "https://live.us.sinaimg.cn/001X2Yf3jx07lZ5zdgGA070d010006200k01.m3u8"
  },
  {
    "title": "徐伊人的电台（回放生成中）",
    "subTitle": {
      "raw": "想来聊会天～",
      "base64": "5oOz5p2l6IGK5Lya5aSp772e"
    },
    "picPath": [
      "https://source.48.cn/mediasource/live/1529326822786pI2cfoSv36.jpg",
      "https://source.48.cn/mediasource/live/15178419357742Y6PCilIxf.jpg"
    ],
    "startTime": {
      "timestamp": 1531323211626,
      "datetime": "2018-07-11T23:33:31Z"
    },
    "memberId": 43,
    "liveType": 2,
    "streamPath": "https://mp4.48.cn/live/0bb8ed4b-ed87-41cc-89fb-12285faa7de5.mp4"
  },
  {
    "title": "徐伊人的直播间（回放生成中）",
    "subTitle": {
      "raw": "～",
      "base64": "772e"
    },
    "picPath": [
      "https://source.48.cn/mediasource/live/1528387341346f9JZy3Jm4L.jpg"
    ],
    "startTime": {
      "timestamp": 1530618394427,
      "datetime": "2018-07-03T19:46:34Z"
    },
    "memberId": 43,
    "liveType": 1,
    "streamPath": "https://live.us.sinaimg.cn/004v8pKJjx07lKwCQ6zC070d010009lP0k01.m3u8"
  },
  {
    "title": "徐伊人的电台（回放生成中）",
    "subTitle": {
      "raw": "想来聊会天～",
      "base64": "5oOz5p2l6IGK5Lya5aSp772e"
    },
    "picPath": [
      "https://source.48.cn/mediasource/live/1529326822786pI2cfoSv36.jpg",
      "https://source.48.cn/mediasource/live/15178419357742Y6PCilIxf.jpg"
    ],
    "startTime": {
      "timestamp": 1530101094104,
      "datetime": "2018-06-27T20:04:54Z"
    },
    "memberId": 43,
    "liveType": 2,
    "streamPath": "https://mp4.48.cn/live/81c49f0d-54c2-40d7-aea2-ad1b47749120.mp4"
  },
  {
    "title": "徐伊人的直播间（回放生成中）",
    "subTitle": {
      "raw": "～",
      "base64": "772e"
    },
    "picPath": [
      "https://source.48.cn/mediasource/live/1528387341346f9JZy3Jm4L.jpg"
    ],
    "startTime": {
      "timestamp": 1529766911449,
      "datetime": "2018-06-23T23:15:11Z"
    },
    "memberId": 43,
    "liveType": 1,
    "streamPath": "https://live.us.sinaimg.cn/002tPtLZjx07luL62ARW070d010005120k01.m3u8"
  },
  {
    "title": "徐伊人的直播间（回放生成中）",
    "subTitle": {
      "raw": "～",
      "base64": "772e"
    },
    "picPath": [
      "https://source.48.cn/mediasource/live/1528387341346f9JZy3Jm4L.jpg"
    ],
    "startTime": {
      "timestamp": 1529412571283,
      "datetime": "2018-06-19T20:49:31Z"
    },
    "memberId": 43,
    "liveType": 1,
    "streamPath": "https://live.us.sinaimg.cn/002G9HHyjx07lof1lwmH070d0100076y0k01.m3u8"
  },
  {
    "title": "徐伊人的电台（回放生成中）",
    "subTitle": {
      "raw": "想来聊会天～",
      "base64": "5oOz5p2l6IGK5Lya5aSp772e"
    },
    "picPath": [
      "https://source.48.cn/mediasource/live/1529326822786pI2cfoSv36.jpg",
      "https://source.48.cn/mediasource/live/15178419357742Y6PCilIxf.jpg"
    ],
    "startTime": {
      "timestamp": 1529326822953,
      "datetime": "2018-06-18T21:00:22Z"
    },
    "memberId": 43,
    "liveType": 2,
    "streamPath": "https://mp6.48.cn/live/078c307d-e4cb-4ddb-a6db-962aa0ba5053.mp4"
  },
  {
    "title": "徐伊人的电台（回放生成中）",
    "subTitle": {
      "raw": "想来聊会天～",
      "base64": "5oOz5p2l6IGK5Lya5aSp772e"
    },
    "picPath": [
      "https://source.48.cn/mediasource/live/1526132601035O8SfIZECaB.jpg",
      "https://source.48.cn/mediasource/live/15178419357742Y6PCilIxf.jpg"
    ],
    "startTime": {
      "timestamp": 1529239810321,
      "datetime": "2018-06-17T20:50:10Z"
    },
    "memberId": 43,
    "liveType": 2,
    "streamPath": "https://mp6.48.cn/live/b7fed3f4-9347-4622-bdce-b238d3d21fec.mp4"
  },
  {
    "title": "徐伊人的直播间（回放生成中）",
    "subTitle": {
      "raw": "～",
      "base64": "772e"
    },
    "picPath": [
      "https://source.48.cn/mediasource/live/1528387341346f9JZy3Jm4L.jpg"
    ],
    "startTime": {
      "timestamp": 1528387341478,
      "datetime": "2018-06-08T00:02:21Z"
    },
    "memberId": 43,
    "liveType": 1,
    "streamPath": "https://live.us.sinaimg.cn/002mzbR1jx07l5kXdVfO070d010009nA0k01.m3u8"
  },
  {
    "title": "徐伊人的电台（回放生成中）",
    "subTitle": {
      "raw": "想来聊会天～",
      "base64": "5oOz5p2l6IGK5Lya5aSp772e"
    },
    "picPath": [
      "https://source.48.cn/mediasource/live/1526132601035O8SfIZECaB.jpg",
      "https://source.48.cn/mediasource/live/15178419357742Y6PCilIxf.jpg"
    ],
    "startTime": {
      "timestamp": 1527694711795,
      "datetime": "2018-05-30T23:38:31Z"
    },
    "memberId": 43,
    "liveType": 2,
    "streamPath": "https://mp6.48.cn/live/2fdcb24b-ab12-4c00-8881-b6137a4d4d03.mp4"
  },
  {
    "title": "徐伊人的电台（回放生成中）",
    "subTitle": {
      "raw": "想来聊会天～",
      "base64": "5oOz5p2l6IGK5Lya5aSp772e"
    },
    "picPath": [
      "https://source.48.cn/mediasource/live/1526132601035O8SfIZECaB.jpg",
      "https://source.48.cn/mediasource/live/15178419357742Y6PCilIxf.jpg"
    ],
    "startTime": {
      "timestamp": 1527693962177,
      "datetime": "2018-05-30T23:26:02Z"
    },
    "memberId": 43,
    "liveType": 2,
    "streamPath": "https://mp6.48.cn/live/ec2ac6a9-6f1a-4160-bbbc-1b860d062ff5.mp4"
  },
  {
    "title": "徐伊人的直播间（回放生成中）",
    "subTitle": {
      "raw": "～",
      "base64": "772e"
    },
    "picPath": [
      "https://source.48.cn/mediasource/live/1526223453546I1s0qdH8uo.jpg"
    ],
    "startTime": {
      "timestamp": 1527252947027,
      "datetime": "2018-05-25T20:55:47Z"
    },
    "memberId": 43,
    "liveType": 1,
    "streamPath": "https://live.us.sinaimg.cn/002GYoLnjx07kKmWOn3y070d010006U80k01.m3u8"
  },
  {
    "title": "徐伊人的直播间（回放生成中）",
    "subTitle": {
      "raw": "～",
      "base64": "772e"
    },
    "picPath": [
      "https://source.48.cn/mediasource/live/1526223453546I1s0qdH8uo.jpg"
    ],
    "startTime": {
      "timestamp": 1526571732165,
      "datetime": "2018-05-17T23:42:12Z"
    },
    "memberId": 43,
    "liveType": 1,
    "streamPath": "https://live.us.sinaimg.cn/000DJAh8jx07kxLPTh71070d010004Ip0k01.m3u8"
  },
  {
    "title": "徐伊人的直播间（回放生成中）",
    "subTitle": {
      "raw": "～",
      "base64": "772e"
    },
    "picPath": [
      "https://source.48.cn/mediasource/live/1526223453546I1s0qdH8uo.jpg"
    ],
    "startTime": {
      "timestamp": 1526223453854,
      "datetime": "2018-05-13T22:57:33Z"
    },
    "memberId": 43,
    "liveType": 1,
    "streamPath": "https://live.us.sinaimg.cn/004hhVyQjx07krmipbCo070d0100005R0k01.m3u8"
  },
  {
    "title": "徐伊人的直播间（回放生成中）",
    "subTitle": {
      "raw": "。",
      "base64": "44CC"
    },
    "picPath": [
      "https://source.48.cn/mediasource/live/151629058700791e0bXlrYu.jpg"
    ],
    "startTime": {
      "timestamp": 1519055210460,
      "datetime": "2018-02-19T23:46:50Z"
    },
    "memberId": 43,
    "liveType": 1,
    "streamPath": "https://live.us.sinaimg.cn/001qdAI4jx07ij1MesLt070d010006vi0k01.m3u8"
  },
  {
    "title": "徐伊人的直播间（回放生成中）",
    "subTitle": {
      "raw": "。",
      "base64": "44CC"
    },
    "picPath": [
      "https://source.48.cn/mediasource/live/151629058700791e0bXlrYu.jpg"
    ],
    "startTime": {
      "timestamp": 1518865637235,
      "datetime": "2018-02-17T19:07:17Z"
    },
    "memberId": 43,
    "liveType": 1,
    "streamPath": "https://mp6.48.cn/live/9227d780-2b0c-4d01-9c3d-8e37b6bbb2e4.mp4"
  },
  {
    "title": "徐伊人的直播间（回放生成中）",
    "subTitle": {
      "raw": "。",
      "base64": "44CC"
    },
    "picPath": [
      "https://source.48.cn/mediasource/live/151629058700791e0bXlrYu.jpg"
    ],
    "startTime": {
      "timestamp": 1518861264869,
      "datetime": "2018-02-17T17:54:24Z"
    },
    "memberId": 43,
    "liveType": 1,
    "streamPath": "https://live.us.sinaimg.cn/002Z5UtSjx07ifo9IbeD070d010002Xi0k01.m3u8"
  },
  {
    "title": "徐伊人的电台（回放生成中）",
    "subTitle": {
      "raw": "一起跨个年吧",
      "base64": "5LiA6LW36Leo5Liq5bm05ZCn"
    },
    "picPath": [
      "https://source.48.cn/mediasource/live/15187082235191uj93Taw0V.jpg",
      "https://source.48.cn/mediasource/live/15178419357742Y6PCilIxf.jpg"
    ],
    "startTime": {
      "timestamp": 1518710305964,
      "datetime": "2018-02-15T23:58:25Z"
    },
    "memberId": 43,
    "liveType": 2,
    "streamPath": "https://mp6.48.cn/live/073cdf2f-dc19-45cf-ae09-ed5bfba5637c.mp4"
  },
  {
    "title": "徐伊人的电台（回放生成中）",
    "subTitle": {
      "raw": "一起跨个年吧",
      "base64": "5LiA6LW36Leo5Liq5bm05ZCn"
    },
    "picPath": [
      "https://source.48.cn/mediasource/live/15187082235191uj93Taw0V.jpg",
      "https://source.48.cn/mediasource/live/15178419357742Y6PCilIxf.jpg"
    ],
    "startTime": {
      "timestamp": 1518708223710,
      "datetime": "2018-02-15T23:23:43Z"
    },
    "memberId": 43,
    "liveType": 2,
    "streamPath": "https://mp6.48.cn/live/e692da6a-714f-47e6-94a9-3046da75ffae.mp4"
  },
  {
    "title": "徐伊人的直播间（回放生成中）",
    "subTitle": {
      "raw": "。",
      "base64": "44CC"
    },
    "picPath": [
      "https://source.48.cn/mediasource/live/151629058700791e0bXlrYu.jpg"
    ],
    "startTime": {
      "timestamp": 1518612195242,
      "datetime": "2018-02-14T20:43:15Z"
    },
    "memberId": 43,
    "liveType": 1,
    "streamPath": "https://live.us.sinaimg.cn/000CsRT3jx07iaSg9BkH070d010008BH0k01.m3u8"
  },
  {
    "title": "徐伊人的直播间（回放生成中）",
    "subTitle": {
      "raw": "。",
      "base64": "44CC"
    },
    "picPath": [
      "https://source.48.cn/mediasource/live/151629058700791e0bXlrYu.jpg"
    ],
    "startTime": {
      "timestamp": 1518012624156,
      "datetime": "2018-02-07T22:10:24Z"
    },
    "memberId": 43,
    "liveType": 1,
    "streamPath": "https://live.us.sinaimg.cn/003fBQNnjx07hZMyAYfC070d010006wb0k01.m3u8"
  },
  {
    "title": "徐伊人的直播间（回放生成中）",
    "subTitle": {
      "raw": "。",
      "base64": "44CC"
    },
    "picPath": [
      "https://source.48.cn/mediasource/live/151629058700791e0bXlrYu.jpg"
    ],
    "startTime": {
      "timestamp": 1517140693422,
      "datetime": "2018-01-28T19:58:13Z"
    },
    "memberId": 43,
    "liveType": 1,
    "streamPath": "https://live.us.sinaimg.cn/0040XuY4jx07hJIUkJvi070d01000a0C0k01.m3u8"
  },
  {
    "title": "徐伊人的直播间（回放生成中）",
    "subTitle": {
      "raw": "。",
      "base64": "44CC"
    },
    "picPath": [
      "https://source.48.cn/mediasource/live/151629058700791e0bXlrYu.jpg"
    ],
    "startTime": {
      "timestamp": 1516290587517,
      "datetime": "2018-01-18T23:49:47Z"
    },
    "memberId": 43,
    "liveType": 1,
    "streamPath": "https://live.us.sinaimg.cn/003Cg5fqjx07htWou0yY070d010004Ym0k01.m3u8"
  },
  {
    "title": "徐伊人的直播间（回放生成中）",
    "subTitle": {
      "raw": "。",
      "base64": "44CC"
    },
    "picPath": [
      "https://source.48.cn/mediasource/live/151577320203228Mt2NQqV4.jpg"
    ],
    "startTime": {
      "timestamp": 1515773202585,
      "datetime": "2018-01-13T00:06:42Z"
    },
    "memberId": 43,
    "liveType": 1,
    "streamPath": "https://live.us.sinaimg.cn/004hE1IBjx07hknqtZtm070d010003NC0k01.m3u8"
  },
  {
    "title": "徐伊人的直播间（回放生成中）",
    "subTitle": {
      "raw": "看过来",
      "base64": "55yL6L+H5p2l"
    },
    "picPath": [
      "https://source.48.cn/mediasource/live/1515496304566XX2ZMt22k2.jpg"
    ],
    "startTime": {
      "timestamp": 1515597969682,
      "datetime": "2018-01-10T23:26:09Z"
    },
    "memberId": 43,
    "liveType": 1,
    "streamPath": "https://live.us.sinaimg.cn/003QaD18jx07hhaDLBtJ070d010006tv0k01.m3u8"
  },
  {
    "title": "徐伊人的直播间（回放生成中）",
    "subTitle": {
      "raw": "看过来",
      "base64": "55yL6L+H5p2l"
    },
    "picPath": [
      "https://source.48.cn/mediasource/live/1515496304566XX2ZMt22k2.jpg"
    ],
    "startTime": {
      "timestamp": 1515503375894,
      "datetime": "2018-01-09T21:09:35Z"
    },
    "memberId": 43,
    "liveType": 1,
    "streamPath": "https://live.us.sinaimg.cn/000R6GoYjx07hft9SHBJ070d01000aLD0k01.m3u8"
  },
  {
    "title": "徐伊人的直播间（回放生成中）",
    "subTitle": {
      "raw": "看过来",
      "base64": "55yL6L+H5p2l"
    },
    "picPath": [
      "https://source.48.cn/mediasource/live/1515496304566XX2ZMt22k2.jpg"
    ],
    "startTime": {
      "timestamp": 1515496304783,
      "datetime": "2018-01-09T19:11:44Z"
    },
    "memberId": 43,
    "liveType": 1,
    "streamPath": "https://live.us.sinaimg.cn/003rWFksjx07hfggh6J9070d010000c60k01.m3u8"
  },
  {
    "title": "徐伊人的直播间（回放生成中）",
    "subTitle": {
      "raw": "#推徐伊人的30天#新年快乐",
      "base64": "I+aOqOW+kOS8iuS6uueahDMw5aSpI+aWsOW5tOW/q+S5kA=="
    },
    "picPath": [
      "https://source.48.cn/mediasource/live/1514128098569N8Xk3DZt1x.jpg"
    ],
    "startTime": {
      "timestamp": 1514722388187,
      "datetime": "2017-12-31T20:13:08Z"
    },
    "memberId": 43,
    "liveType": 1,
    "streamPath": "https://live.us.sinaimg.cn/003VcXMOjx07h15yQepy070d01000eYt0k01.m3u8"
  },
  {
    "title": "徐伊人的直播间（回放生成中）",
    "subTitle": {
      "raw": "#推徐伊人的30天#",
      "base64": "I+aOqOW+kOS8iuS6uueahDMw5aSpIw=="
    },
    "picPath": [
      "https://source.48.cn/mediasource/live/1514128098569N8Xk3DZt1x.jpg"
    ],
    "startTime": {
      "timestamp": 1514465910304,
      "datetime": "2017-12-28T20:58:30Z"
    },
    "memberId": 43,
    "liveType": 1,
    "streamPath": "https://live.us.sinaimg.cn/0043C5W7jx07gWhOB9sY070d010008YK0k01.m3u8"
  },
  {
    "title": "徐伊人的直播间（回放生成中）",
    "subTitle": {
      "raw": "#推徐伊人的30天招募女友",
      "base64": "I+aOqOW+kOS8iuS6uueahDMw5aSp5oub5Yuf5aWz5Y+L"
    },
    "picPath": [
      "https://source.48.cn/mediasource/live/1514128098569N8Xk3DZt1x.jpg"
    ],
    "startTime": {
      "timestamp": 1514128098897,
      "datetime": "2017-12-24T23:08:18Z"
    },
    "memberId": 43,
    "liveType": 1,
    "streamPath": "https://live.us.sinaimg.cn/000n3QqOjx07gQ3BzLsX070d010005jF0k01.m3u8"
  },
  {
    "title": "徐伊人的直播间（回放生成中）",
    "subTitle": {
      "raw": "#推徐伊人的30天#",
      "base64": "I+aOqOW+kOS8iuS6uueahDMw5aSpIw=="
    },
    "picPath": [
      "https://source.48.cn/mediasource/live/1513784507667u0G6yb1N5d.jpg"
    ],
    "startTime": {
      "timestamp": 1513784508522,
      "datetime": "2017-12-20T23:41:48Z"
    },
    "memberId": 43,
    "liveType": 1,
    "streamPath": "https://live.us.sinaimg.cn/003I6J5vjx07gJEWpaZW070d010003gO0k01.m3u8"
  },
  {
    "title": "徐伊人的直播间（回放生成中）",
    "subTitle": {
      "raw": "#推徐伊人的30天#中饭",
      "base64": "I+aOqOW+kOS8iuS6uueahDMw5aSpI+S4remlrQ=="
    },
    "picPath": [
      "https://source.48.cn/mediasource/live/1513561969465NgBX2Z5ebu.jpg"
    ],
    "startTime": {
      "timestamp": 1513561969690,
      "datetime": "2017-12-18T09:52:49Z"
    },
    "memberId": 43,
    "liveType": 1,
    "streamPath": "https://live.us.sinaimg.cn/004lZgx3jx07gFzVc1SM070d010005Kh0k01.m3u8"
  },
  {
    "title": "徐伊人的直播间（回放生成中）",
    "subTitle": {
      "raw": "#推徐伊人的30天#～",
      "base64": "I+aOqOW+kOS8iuS6uueahDMw5aSpI++9ng=="
    },
    "picPath": [
      "https://source.48.cn/mediasource/live/15134161480207F2Ev8WtCO.jpg"
    ],
    "startTime": {
      "timestamp": 1513416148235,
      "datetime": "2017-12-16T17:22:28Z"
    },
    "memberId": 43,
    "liveType": 1,
    "streamPath": "https://live.us.sinaimg.cn/002WOfvmjx07gCSioUFG070d010004EQ0k01.m3u8"
  },
  {
    "title": "徐伊人的直播间（回放生成中）",
    "subTitle": {
      "raw": "#推徐伊人的30天#～",
      "base64": "I+aOqOW+kOS8iuS6uueahDMw5aSpI++9ng=="
    },
    "picPath": [
      "https://source.48.cn/mediasource/live/1512957788438W498gC1xju.jpg"
    ],
    "startTime": {
      "timestamp": 1513265783023,
      "datetime": "2017-12-14T23:36:23Z"
    },
    "memberId": 43,
    "liveType": 1,
    "streamPath": "https://live.us.sinaimg.cn/0005hhzajx07gA71oO6H070d0100065y0k01.m3u8"
  },
  {
    "title": "徐伊人的直播间（回放生成中）",
    "subTitle": {
      "raw": "#推徐伊人的30天#周末",
      "base64": "I+aOqOW+kOS8iuS6uueahDMw5aSpI+WRqOacqw=="
    },
    "picPath": [
      "https://source.48.cn/mediasource/live/15125735669136nU8vp514o.jpg"
    ],
    "startTime": {
      "timestamp": 1512825554350,
      "datetime": "2017-12-09T21:19:14Z"
    },
    "memberId": 43,
    "liveType": 1,
    "streamPath": "https://live.us.sinaimg.cn/000wEfhBjx07grY7z5IP070d01000sOg0k01.m3u8"
  },
  {
    "title": "徐伊人的直播间（回放生成中）",
    "subTitle": {
      "raw": "#推徐伊人的30天#周末",
      "base64": "I+aOqOW+kOS8iuS6uueahDMw5aSpI+WRqOacqw=="
    },
    "picPath": [
      "https://source.48.cn/mediasource/live/15125735669136nU8vp514o.jpg"
    ],
    "startTime": {
      "timestamp": 1512816795992,
      "datetime": "2017-12-09T18:53:15Z"
    },
    "memberId": 43,
    "liveType": 1,
    "streamPath": "https://live.us.sinaimg.cn/003ABIprjx07grNfxdY3070d01000lbr0k01.m3u8"
  },
  {
    "title": "徐伊人的直播间（回放生成中）",
    "subTitle": {
      "raw": "#推徐伊人的30天#早？中饭吧",
      "base64": "I+aOqOW+kOS8iuS6uueahDMw5aSpI+aXqe+8n+S4remlreWQpw=="
    },
    "picPath": [
      "https://source.48.cn/mediasource/live/15125735669136nU8vp514o.jpg"
    ],
    "startTime": {
      "timestamp": 1512786202346,
      "datetime": "2017-12-09T10:23:22Z"
    },
    "memberId": 43,
    "liveType": 1,
    "streamPath": "https://live.us.sinaimg.cn/000H6Buxjx07grfBLtrW070d01000zUg0k01.m3u8"
  },
  {
    "title": "徐伊人的直播间（回放生成中）",
    "subTitle": {
      "raw": "#推徐伊人的30天#～",
      "base64": "I+aOqOW+kOS8iuS6uueahDMw5aSpI++9ng=="
    },
    "picPath": [
      "https://source.48.cn/mediasource/live/15125735669136nU8vp514o.jpg"
    ],
    "startTime": {
      "timestamp": 1512574570510,
      "datetime": "2017-12-06T23:36:10Z"
    },
    "memberId": 43,
    "liveType": 1,
    "streamPath": "https://mp6.48.cn/live/ef891523-5736-4c73-977f-2499ad60e9f4.mp4"
  },
  {
    "title": "徐伊人的直播间（回放生成中）",
    "subTitle": {
      "raw": "#推徐伊人的30天#做个早饭～",
      "base64": "I+aOqOW+kOS8iuS6uueahDMw5aSpI+WBmuS4quaXqemlre+9ng=="
    },
    "picPath": [
      "https://source.48.cn/mediasource/live/1512439125390QTUPI1MgR4.jpg"
    ],
    "startTime": {
      "timestamp": 1512439125504,
      "datetime": "2017-12-05T09:58:45Z"
    },
    "memberId": 43,
    "liveType": 1,
    "streamPath": "https://live.us.sinaimg.cn/004viVTPjx07gkPwgTLp070d01000rcU0k01.m3u8"
  },
  {
    "title": "徐伊人的直播间（回放生成中）",
    "subTitle": {
      "raw": "#推徐伊人的30天#随便瞎聊聊",
      "base64": "I+aOqOW+kOS8iuS6uueahDMw5aSpI+maj+S+v+eejuiBiuiBig=="
    },
    "picPath": [
      "https://source.48.cn/mediasource/live/1512115407774XXp18l4daK.jpg"
    ],
    "startTime": {
      "timestamp": 1512115407903,
      "datetime": "2017-12-01T16:03:27Z"
    },
    "memberId": 43,
    "liveType": 1,
    "streamPath": "https://live.us.sinaimg.cn/002nm2tvjx07geRR0w5O070d01000zzR0k01.m3u8"
  }
]
